photompy/__init__.py
photompy/calculate.py
photompy/exceptions.py
photompy/ies.py
photompy/ies_header.py
photompy/interpolate.py
photompy/photometry.py
photompy/plot.py
photompy/read.py
photompy/write.py
photompy-0.1.4.dist-info/LICENSE.txt
photompy-0.1.4.dist-info/METADATA
photompy-0.1.4.dist-info/WHEEL
photompy-0.1.4.dist-info/top_level.txt
photompy-0.1.4.dist-info/zip-safe
photompy-0.1.4.dist-info/RECORD
