Metadata-Version: 2.1
Name: photompy
Version: 0.1.4
Summary: A library for reading, writing, and viewing photometric files.
Home-page: https://github.com/jvbelenky/photompy
Author: J. Vivian Belenky
Author-email: j.vivian.belenky@outlook.com
Classifier: Programming Language :: Python :: 3
Classifier: Operating System :: OS Independent
Classifier: License :: OSI Approved :: MIT License
Requires-Python: >=3.8
License-File: LICENSE.txt
Requires-Dist: numpy
Requires-Dist: matplotlib
